[
  {
    "id": "skill.reference.corporate-client-coverage-lens",
    "type": "reference",
    "capability": "analyze",
    "title": "Corporate Client Coverage Lens",
    "display_name_zh": "对公客户覆盖视角",
    "path": "skills/reference/corporate-client-coverage-lens",
    "entry": "skills/reference/corporate-client-coverage-lens/SKILL.md",
    "summary": "提供对公客户相关任务的专业观察视角、优先级规则和关键对象判断。",
    "audience": ["finance-learner", "bank-practitioner"],
    "task_patterns": ["客户推进", "首访准备", "关键对象判断", "岗位视角", "优先级判断"],
    "when_to_use": "需要先站在成熟对公客户覆盖视角判断重点、对象和推进节奏时。",
    "not_for": "需要最新外部事实核验、审批授信结论或纯产品参数查询时。",
    "inputs": ["问题场景", "当前卡点", "关键对象"],
    "outputs": ["视角判断", "优先级排序", "关键对象提示", "建议补读的 skill 和 knowledge"],
    "related_skills": [
      "skill.reference.problem-opportunity-framework",
      "skill.reference.client-advance-framework",
      "skill.action.market-corporate-client",
      "skill.action.accompany-corporate-client",
      "skill.action.report-decision-brief"
    ],
    "related_knowledge": [
      "knowledge.banks.ceb.corporate-settlement.basic-settlement",
      "knowledge.banks.ceb.transaction-banking.yangguang-e-pay",
      "knowledge.banks.ceb.trade-finance.yangguang-electricity-certificate",
      "knowledge.common.banker-thinking.top-performer",
      "knowledge.common.economics.business-basics",
      "knowledge.common.sales.consultative-b2b",
      "knowledge.common.psychology.business-communication"
    ],
    "related_prompts": [
      "prompt.skill.reference.corporate-client-coverage-lens"
    ]
  },
  {
    "id": "skill.reference.problem-opportunity-framework",
    "type": "reference",
    "capability": "analyze",
    "title": "Problem Opportunity Framework",
    "display_name_zh": "问题-机会框架",
    "path": "skills/reference/problem-opportunity-framework",
    "entry": "skills/reference/problem-opportunity-framework/SKILL.md",
    "summary": "帮助识别真实问题、可验证的机会假设和下一步验证动作。",
    "audience": ["finance-learner", "bank-practitioner"],
    "task_patterns": ["问题分析", "机会判断", "切入口判断", "客户卡点", "优先级"],
    "when_to_use": "需要先判断问题是否成立、机会是否值得验证、下一步应该验证什么时。",
    "not_for": "需要直接输出完整行动方案或最新外部数据结论时。",
    "inputs": ["当前场景", "已知问题", "初步线索"],
    "outputs": ["问题扫描", "机会假设", "下一步验证动作"],
    "related_skills": [
      "skill.reference.corporate-client-coverage-lens",
      "skill.reference.client-advance-framework",
      "skill.action.market-corporate-client"
    ],
    "related_knowledge": [
      "knowledge.banks.ceb.corporate-settlement.basic-settlement",
      "knowledge.banks.ceb.transaction-banking.yangguang-e-pay",
      "knowledge.banks.ceb.trade-finance.yangguang-electricity-certificate"
    ],
    "related_prompts": []
  },
  {
    "id": "skill.reference.client-advance-framework",
    "type": "reference",
    "capability": "execute",
    "title": "Client Advance Framework",
    "display_name_zh": "客户推进框架",
    "path": "skills/reference/client-advance-framework",
    "entry": "skills/reference/client-advance-framework/SKILL.md",
    "summary": "把沟通结果收束为目标、动作、责任人和时间点，避免推进掉线。",
    "audience": ["finance-learner", "bank-practitioner"],
    "task_patterns": ["下一步怎么推进", "客户跟进", "闭环", "谁做什么", "时间点"],
    "when_to_use": "需要把一次沟通或一次判断推进成可执行的下一步动作时。",
    "not_for": "需要直接输出事实查询结果或替代场景编排时。",
    "inputs": ["当前关系阶段", "关键卡点", "协同对象"],
    "outputs": ["推进目标", "动作清单", "责任人", "时间点"],
    "related_skills": [
      "skill.reference.problem-opportunity-framework",
      "skill.action.market-corporate-client",
      "skill.action.accompany-corporate-client"
    ],
    "related_knowledge": [
      "knowledge.common.sales.consultative-b2b",
      "knowledge.common.psychology.business-communication"
    ],
    "related_prompts": []
  },
  {
    "id": "skill.reference.client-visit-opening",
    "type": "reference",
    "capability": "analyze",
    "title": "Client Visit Opening",
    "display_name_zh": "客户拜访开场框架",
    "path": "skills/reference/client-visit-opening",
    "entry": "skills/reference/client-visit-opening/SKILL.md",
    "summary": "提供客户拜访开场时机、信任建立策略和客户状态快速评估的判断框架。",
    "audience": ["finance-learner", "bank-practitioner"],
    "task_patterns": ["客户拜访开场", "首访开场", "开场策略", "客户配合度", "开场提问方向"],
    "when_to_use": "准备或复盘对公客户拜访开场，需要判断用哪种开场策略、第一问往哪里走时。",
    "not_for": "需要完整拜访场景编排、具体话术模板或首次拜访后的持续跟进设计时。",
    "inputs": ["客户关系基础", "会谈对象", "当前拜访目标", "已知客户状态"],
    "outputs": ["开场策略", "第一个问题方向", "客户配合度预判", "使用边界提示"],
    "related_skills": [
      "skill.action.market-corporate-client",
      "skill.reference.problem-opportunity-framework",
      "skill.reference.client-advance-framework"
    ],
    "related_knowledge": [
      "knowledge.common.sales.consultative-b2b"
    ],
    "related_prompts": []
  },
  {
    "id": "skill.reference.decision-brief-framework",
    "type": "reference",
    "capability": "communicate",
    "title": "Decision Brief Framework",
    "display_name_zh": "拍板简报框架",
    "path": "skills/reference/decision-brief-framework",
    "entry": "skills/reference/decision-brief-framework/SKILL.md",
    "summary": "把复杂事项整理为领导可快速拍板的表达结构。",
    "audience": ["finance-learner", "bank-practitioner"],
    "task_patterns": ["向领导汇报", "拍板简报", "口头汇报", "书面简报"],
    "when_to_use": "需要把复杂事项压缩成可判断、可拍板、可转述的表达结构时。",
    "not_for": "缺少基础事实且尚未完成事实收集时。",
    "inputs": ["背景事实", "关键变化", "卡点", "建议动作"],
    "outputs": ["一句话结论", "关键事实", "卡点", "建议动作", "拍板项"],
    "related_skills": [
      "skill.action.report-decision-brief"
    ],
    "related_knowledge": [
      "knowledge.common.banker-thinking.top-performer",
      "knowledge.common.psychology.business-communication"
    ],
    "related_prompts": []
  },
  {
    "id": "skill.reference.team-followup-framework",
    "type": "reference",
    "capability": "execute",
    "title": "Team Followup Framework",
    "display_name_zh": "团队跟进框架",
    "path": "skills/reference/team-followup-framework",
    "entry": "skills/reference/team-followup-framework/SKILL.md",
    "summary": "帮助拆任务、定责任、看信号和做复盘，形成稳定管理闭环。",
    "audience": ["finance-learner", "bank-practitioner"],
    "task_patterns": ["团队跟进", "检查点", "复盘", "责任人", "闭环"],
    "when_to_use": "需要把多人协同事项管成一块可跟、可查、可复盘的板子时。",
    "not_for": "只需要单次表达或只回答概念问题时。",
    "inputs": ["事项清单", "负责人", "截止时间", "当前卡点"],
    "outputs": ["最小管理板", "检查节奏", "复盘提醒"],
    "related_skills": [
      "skill.action.accompany-corporate-client",
      "skill.action.report-decision-brief"
    ],
    "related_knowledge": [
      "knowledge.common.banker-thinking.top-performer",
      "knowledge.common.psychology.business-communication"
    ],
    "related_prompts": []
  },
  {
    "id": "skill.action.market-corporate-client",
    "type": "action",
    "capability": "execute",
    "title": "Market Corporate Client",
    "display_name_zh": "对公客户首访推进",
    "path": "skills/action/market-corporate-client",
    "entry": "skills/action/market-corporate-client/SKILL.md",
    "summary": "面向首访或首次触达场景，组织诊断、开场、切入口和下一步动作。",
    "audience": ["bank-practitioner"],
    "task_patterns": ["首访客户", "客户开场", "营销切入口", "首次会谈"],
    "when_to_use": "准备首次接触客户并需要一套可直接拿去用的推进结构时。",
    "not_for": "持续陪伴、团队管理闭环或纯知识问答时。",
    "inputs": ["行业", "当前卡点", "会谈对象", "期望达成的最小结果"],
    "outputs": ["场景初判", "推荐切入口", "首次会谈目标", "会后推进动作", "客户追问回答"],
    "related_skills": [
      "skill.reference.problem-opportunity-framework",
      "skill.reference.client-advance-framework",
      "skill.reference.corporate-client-coverage-lens"
    ],
    "related_knowledge": [
      "knowledge.banks.ceb.corporate-settlement.basic-settlement",
      "knowledge.banks.ceb.transaction-banking.yangguang-e-pay",
      "knowledge.banks.ceb.trade-finance.yangguang-electricity-certificate",
      "knowledge.common.sales.consultative-b2b",
      "knowledge.common.psychology.business-communication"
    ],
    "related_prompts": [
      "prompt.skill.action.market-corporate-client"
    ]
  },
  {
    "id": "skill.action.accompany-corporate-client",
    "type": "action",
    "capability": "execute",
    "title": "Accompany Corporate Client",
    "display_name_zh": "对公客户持续推进",
    "path": "skills/action/accompany-corporate-client",
    "entry": "skills/action/accompany-corporate-client/SKILL.md",
    "summary": "面向会后跟进、问题闭环和关系经营，输出本次跟进动作与下一次触达计划。",
    "audience": ["bank-practitioner"],
    "task_patterns": ["客户跟进", "问题闭环", "会后推进", "关系经营"],
    "when_to_use": "进入持续跟进阶段并需要把问题、协同和触达节奏组织起来时。",
    "not_for": "首次触达准备、拍板汇报或纯概念解释时。",
    "inputs": ["当前关系阶段", "待回应问题", "内部协同角色", "下一次触达目标"],
    "outputs": ["客户关系温度", "待回应问题清单", "本次跟进动作", "内部协同清单", "下一次触达计划"],
    "related_skills": [
      "skill.reference.client-advance-framework",
      "skill.reference.team-followup-framework",
      "skill.reference.corporate-client-coverage-lens"
    ],
    "related_knowledge": [
      "knowledge.banks.ceb.corporate-settlement.basic-settlement",
      "knowledge.banks.ceb.transaction-banking.yangguang-e-pay",
      "knowledge.banks.ceb.trade-finance.yangguang-electricity-certificate",
      "knowledge.common.sales.consultative-b2b",
      "knowledge.common.psychology.business-communication"
    ],
    "related_prompts": [
      "prompt.skill.action.accompany-corporate-client"
    ]
  },
  {
    "id": "skill.action.report-decision-brief",
    "type": "action",
    "capability": "communicate",
    "title": "Report Decision Brief",
    "display_name_zh": "向领导汇报与拍板",
    "path": "skills/action/report-decision-brief",
    "entry": "skills/action/report-decision-brief/SKILL.md",
    "summary": "面向汇报与提请拍板场景，组织事实、变化、卡点和建议动作。",
    "audience": ["finance-learner", "bank-practitioner", "manager"],
    "task_patterns": ["向领导汇报", "拍板", "书面简报", "口头汇报"],
    "when_to_use": "需要快速把复杂事项整理成可拍板的口头或书面汇报时。",
    "not_for": "还没完成基础事实采集、或需要持续跟进闭环时。",
    "inputs": ["汇报类型", "当前进展", "当前卡点", "期望领导支持事项"],
    "outputs": ["一句话结论", "关键事实", "当前卡点", "建议动作", "需要拍板项"],
    "related_skills": [
      "skill.reference.decision-brief-framework",
      "skill.reference.team-followup-framework"
    ],
    "related_knowledge": [
      "knowledge.banks.ceb.corporate-settlement.basic-settlement",
      "knowledge.banks.ceb.transaction-banking.yangguang-e-pay",
      "knowledge.banks.ceb.trade-finance.yangguang-electricity-certificate",
      "knowledge.common.banker-thinking.top-performer",
      "knowledge.common.economics.business-basics",
      "knowledge.common.psychology.business-communication"
    ],
    "related_prompts": [
      "prompt.skill.action.report-decision-brief"
    ]
  },
  {
    "id": "skill.action.interpret-financial-signal",
    "type": "action",
    "capability": "analyze",
    "title": "Interpret Financial Signal",
    "display_name_zh": "金融信息解读与落地",
    "path": "skills/action/interpret-financial-signal",
    "entry": "skills/action/interpret-financial-signal/SKILL.md",
    "summary": "把政策、新闻、产品、竞品、客户变化等新信息解读为银行/金融工作中的影响路径和落地参考。",
    "audience": ["finance-learner", "bank-practitioner", "manager"],
    "task_patterns": ["政策解读", "新闻解读", "产品解读", "竞品分析", "客户变化", "信息研判", "落地建议"],
    "when_to_use": "用户带来新信息并希望判断它对金融能力成长、客户推进、汇报或沉淀有什么实际意义时。",
    "not_for": "只需要查询稳定公开事实、或需要内部审批结论、授信定价承诺时。",
    "inputs": ["信息原文或摘要", "用户身份或使用场景", "期望产出"],
    "outputs": ["一句话结论", "信息类型判断", "影响路径", "落地参考方向", "待确认信息", "后续追问方向", "边界提示"],
    "related_skills": [
      "skill.reference.problem-opportunity-framework",
      "skill.reference.corporate-client-coverage-lens",
      "skill.reference.client-advance-framework",
      "skill.reference.decision-brief-framework",
      "skill.action.market-corporate-client",
      "skill.action.accompany-corporate-client",
      "skill.action.report-decision-brief",
      "skill.action.distill-and-curate",
      "skill.action.query-finhot"
    ],
    "related_knowledge": [
      "knowledge.banks.ceb.corporate-settlement.basic-settlement",
      "knowledge.banks.ceb.transaction-banking.yangguang-e-pay",
      "knowledge.banks.ceb.trade-finance.yangguang-electricity-certificate",
      "knowledge.common.banker-thinking.top-performer",
      "knowledge.common.economics.business-basics",
      "knowledge.common.sales.consultative-b2b",
      "knowledge.common.psychology.business-communication"
    ],
    "related_prompts": [
      "prompt.skill.action.interpret-financial-signal"
    ]
  },
  {
    "id": "skill.action.distill-and-curate",
    "type": "action",
    "capability": "distill",
    "title": "Distill And Curate",
    "display_name_zh": "蒸馏与整理",
    "path": "skills/action/distill-and-curate",
    "entry": "skills/action/distill-and-curate/SKILL.md",
    "summary": "把公开材料、案例和个人经验增量整理成 reference skill、action skill、knowledge 或 private 草稿。",
    "audience": ["maintainer", "contributor", "finance-learner", "bank-practitioner"],
    "task_patterns": ["蒸馏资料", "整理知识", "沉淀经验", "public candidate", "private-first"],
    "when_to_use": "需要把材料和经验整理成可复用仓库资产，并明确公开边界时。",
    "not_for": "只求当轮答案、不需要沉淀或没有任何材料输入时。",
    "inputs": ["输入材料", "目标用途", "public/private 意图", "已有资产现状"],
    "outputs": ["资产归类判断", "目标路径", "建议文件", "增量摘要", "公开边界提示"],
    "related_skills": [
      "skill.reference.problem-opportunity-framework",
      "skill.reference.client-advance-framework"
    ],
    "related_knowledge": [
      "knowledge.common.banker-thinking.top-performer",
      "knowledge.common.sales.consultative-b2b",
      "knowledge.common.psychology.business-communication"
    ],
    "related_prompts": []
  },
  {
    "id": "skill.reference.executive-briefing-decision-support",
    "type": "reference",
    "capability": "communicate",
    "title": "Executive Briefing Decision Support",
    "display_name_zh": "向上汇报与决策支持判断框架",
    "path": "skills/reference/executive-briefing-decision-support",
    "entry": "skills/reference/executive-briefing-decision-support/SKILL.md",
    "summary": "在向领导汇报前，判断汇报类型、选择结构、识别决策点、预判风险的判断框架。",
    "audience": ["finance-learner", "bank-practitioner", "manager"],
    "task_patterns": [
      "汇报前怎么判断",
      "汇报结构怎么选",
      "要不要向领导汇报",
      "决策点有哪些",
      "领导会质疑什么",
      "汇报风险预判",
      "同步还是请求还是说服",
      "结论先行还是背景先行",
      "需要领导给什么资源"
    ],
    "when_to_use": "准备向领导汇报前，需要先判断用什么结构、有哪些决策点、预判哪些风险时。",
    "not_for": "需要直接写汇报稿（用 decision-brief-framework 或 report-decision-brief）、或还没有完成基础事实采集时。",
    "inputs": ["汇报主题", "当前进展或背景", "核心卡点或问题", "期望结果"],
    "outputs": [
      "汇报类型判断（同步型/请求型/说服型）",
      "结构选择（结论先行/SCQA/其他）",
      "决策点列表",
      "风险预判",
      "资源需求（量化）",
      "与 related_skills 的使用边界"
    ],
    "related_skills": [
      "skill.reference.decision-brief-framework",
      "skill.action.report-decision-brief",
      "skill.reference.team-followup-framework"
    ],
    "related_knowledge": [
      "knowledge.common.banker-thinking.top-performer",
      "knowledge.common.psychology.business-communication"
    ],
    "related_prompts": [
      "prompt.skill.reference.executive-briefing-decision-support"
    ],
    "boundary": {
      "vs.decision-brief-framework": "判断框架 vs. 结构模板",
      "vs.report-decision-brief": "判断框架 vs. 执行脚本",
      "vs.team-followup-framework": "向上汇报判断 vs. 团队管理闭环"
    }
  },
  {
    "id": "skill.action.client-followup-systematic",
    "type": "action",
    "capability": "execute",
    "title": "Client Followup Systematic",
    "display_name_zh": "客户事项系统跟进",
    "path": "skills/action/client-followup-systematic",
    "entry": "skills/action/client-followup-systematic/SKILL.md",
    "summary": "面向事项推动场景，评估跟进事项状态、判断优先级、设计推动动作并推动闭环。",
    "audience": ["bank-practitioner"],
    "task_patterns": ["事项跟进", "推动闭环", "状态评估", "优先级判断", "动作推动"],
    "when_to_use": "需要系统跟进客户承诺事项、判断优先级、决定下一步推动动作时。",
    "not_for": "关系维护型跟进、会后触达计划或纯概念解释时（用 accompany-corporate-client）。",
    "inputs": ["客户名称（代号）", "事项清单（承诺内容/承诺方/承诺时间/当前状态）", "本次跟进目标"],
    "outputs": ["事项状态评估", "优先级排序", "下一步动作", "协同需求", "风险信号"],
    "related_skills": [
      "skill.reference.client-advance-framework",
      "skill.reference.team-followup-framework",
      "skill.reference.corporate-client-coverage-lens",
      "skill.action.accompany-corporate-client"
    ],
    "related_knowledge": [
      "knowledge.common.sales.consultative-b2b",
      "knowledge.common.banker-thinking.top-performer",
      "knowledge.common.psychology.business-communication"
    ],
    "related_prompts": [
      "prompt.skill.action.client-followup-systematic"
    ]
  },
  {
    "id": "skill.action.product-matching-boundary",
    "type": "action",
    "capability": "execute",
    "title": "Product Matching Boundary",
    "display_name_zh": "产品匹配与边界提示",
    "path": "skills/action/product-matching-boundary",
    "entry": "skills/action/product-matching-boundary/SKILL.md",
    "summary": "面向需求定型后场景，判断哪类产品适合、哪些边界不能碰、是否需要跨条线协同。",
    "audience": ["bank-practitioner"],
    "task_patterns": ["产品匹配", "边界提示", "合规判断", "协同需求", "产品适配"],
    "when_to_use": "需求诊断完成后需要判断产品适配、核查合规边界、设计协同方案时。",
    "not_for": "首访开场、需求探索、或只需要产品参数查询时（用 market-corporate-client 或 knowledge 查询）。",
    "inputs": ["客户需求定型结论", "客户基本情况（行业/规模/经营状态）", "客户归属（公司/零售/普惠/同业）"],
    "outputs": ["产品候选列表（按适配度排序）", "边界提示", "协同需求", "下一轮动作建议"],
    "related_skills": [
      "skill.reference.problem-opportunity-framework",
      "skill.reference.corporate-client-coverage-lens",
      "skill.action.market-corporate-client",
      "skill.action.client-followup-systematic"
    ],
    "related_knowledge": [
      "knowledge.banks.ceb.corporate-settlement.basic-settlement",
      "knowledge.banks.ceb.transaction-banking.yangguang-e-pay",
      "knowledge.banks.ceb.trade-finance.yangguang-electricity-certificate",
      "knowledge.banks.ceb.supply-chain.yangguang-supply-chain",
      "knowledge.banks.ceb.inclusive-finance.scenario-map",
      "knowledge.common.sales.consultative-b2b"
    ],
    "related_prompts": [
      "prompt.skill.action.product-matching-boundary"
    ]
  },
  {
    "id": "skill.reference.enterprise-cash-flow-judgment",
    "type": "reference",
    "capability": "analyze",
    "title": "Enterprise Cash Flow Judgment",
    "display_name_zh": "企业现金流判断",
    "path": "skills/reference/enterprise-cash-flow-judgment",
    "entry": "skills/reference/enterprise-cash-flow-judgment/SKILL.md",
    "summary": "从银行信审视角判断企业现金流质量、三流平衡与信贷相关信号。",
    "audience": ["finance-learner", "bank-practitioner"],
    "task_patterns": ["现金流是否健康", "企业现金生成能力", "偿债能力评估", "经营现金流", "企业现金质量", "财报现金流分析", "还款能力"],
    "when_to_use": "需要从财报中判断企业真实现金生成能力、判断客户现金流是否健康可持续、评估融资需求与现金状态匹配度时。",
    "not_for": "需要精确财务预测模型、行业对比基准数据、最新监管政策即时解读时。",
    "inputs": ["近三年资产负债表（简化版）", "近三年现金流量表（经营/投资/融资三段）", "近三年利润表"],
    "outputs": ["现金流质量判断", "三流平衡状态", "预警信号标注", "还缺信息提示"],
    "related_skills": [
      "skill.reference.corporate-client-coverage-lens",
      "skill.reference.problem-opportunity-framework",
      "skill.action.market-corporate-client",
      "skill.action.product-matching-boundary",
      "skill.action.report-decision-brief"
    ],
    "related_knowledge": [
      "knowledge.common.economics.business-basics",
      "knowledge.banks.ceb.corporate-settlement.yangguang-cash-management",
      "knowledge.banks.ceb.trade-finance.yangguang-electricity-certificate",
      "knowledge.banks.ceb.transaction-banking.yangguang-e-pay"
    ],
    "related_prompts": []
  },
  {
    "id": "skill.reference.financial-statement-reading-lens",
    "type": "reference",
    "capability": "analyze",
    "title": "Financial Statement Reading Lens",
    "display_name_zh": "财报阅读专业视角",
    "path": "skills/reference/financial-statement-reading-lens",
    "entry": "skills/reference/financial-statement-reading-lens/SKILL.md",
    "summary": "从银行对公业务视角阅读财报，判断先看什么、如何看质量、如何表达发现。",
    "audience": ["finance-learner", "bank-practitioner"],
    "task_patterns": ["财报阅读", "财务分析", "现金流判断", "偿债能力", "客户评估报告", "财务风险识别"],
    "when_to_use": "客户拜访、客户评估或会议表达前，需要快速建立企业财务状况的专业判断框架时。",
    "not_for": "需要直接输出授信、定价、审批结论，或需要精确财务预测模型时。",
    "inputs": ["近三年资产负债表", "近三年现金流量表", "近三年利润表"],
    "outputs": ["优先阅读顺序", "财务质量判断", "风险信号", "缺失信息提示"],
    "related_skills": [
      "skill.reference.enterprise-cash-flow-judgment",
      "skill.reference.industry-analysis-basics",
      "skill.reference.corporate-client-coverage-lens",
      "skill.action.client-needs-diagnosis",
      "skill.action.report-decision-brief"
    ],
    "related_knowledge": [
      "knowledge.common.economics.business-basics"
    ],
    "related_prompts": []
  },
  {
    "id": "skill.action.client-needs-diagnosis",
    "type": "action",
    "capability": "analyze",
    "title": "Client Needs Diagnosis",
    "display_name_zh": "客户需求诊断",
    "path": "skills/action/client-needs-diagnosis",
    "entry": "skills/action/client-needs-diagnosis/SKILL.md",
    "summary": "面向对公客户，系统判断客户当前最可能的金融需求类型，为产品匹配提供输入。",
    "audience": ["bank-practitioner"],
    "task_patterns": ["客户需求诊断", "需求归类", "需求判断", "拜访前判断", "沟通中归类"],
    "when_to_use": "拜访前想先判断客户最可能的金融需求方向、或需要给 product-matching-boundary 提供明确需求定型结论时。",
    "not_for": "首访开场、关系维护、或只需要产品参数查询时（用 market-corporate-client 或 knowledge 查询）。",
    "inputs": ["客户基本情况（行业/规模/主营业务至少一项）", "已知信号（业务动作/痛点/变化/表达至少一项）"],
    "outputs": ["需求类型判断（一级+二级）", "信号依据", "置信度评估（高/中/低）", "待验证项", "建议下一步"],
    "related_skills": [
      "skill.reference.problem-opportunity-framework",
      "skill.reference.corporate-client-coverage-lens",
      "skill.action.market-corporate-client",
      "skill.action.product-matching-boundary"
    ],
    "related_knowledge": [
      "knowledge.banks.ceb.corporate-settlement.basic-settlement",
      "knowledge.banks.ceb.transaction-banking.yangguang-e-pay",
      "knowledge.banks.ceb.trade-finance.yangguang-electricity-certificate",
      "knowledge.banks.ceb.transaction-banking.yangguang-supply-chain",
      "knowledge.banks.ceb.inclusive-finance.scenario-map",
      "knowledge.common.sales.consultative-b2b",
      "knowledge.common.economics.business-basics"
    ],
    "related_prompts": []
  },
  {
    "id": "skill.action.inclusive-finance-scenario-judgment",
    "type": "action",
    "capability": "analyze",
    "title": "Inclusive Finance Scenario Judgment",
    "display_name_zh": "普惠金融场景判断",
    "path": "skills/action/inclusive-finance-scenario-judgment",
    "entry": "skills/action/inclusive-finance-scenario-judgment/SKILL.md",
    "summary": "面向普惠金融场景，快速判断客户是否属于普惠适用范畴，匹配政策层级和产品候选方向。",
    "audience": ["bank-practitioner"],
    "task_patterns": ["普惠金融判断", "场景判断", "小微企业判断", "三农判断", "普惠贷款", "客户是否属于普惠"],
    "when_to_use": "接触新客户判断是否属于普惠金融客群、或需要给 product-matching-boundary 提供普惠场景结论时。",
    "not_for": "需求已经确认为普惠后的产品细节查询（用 knowledge 查询）、或只需要产品参数时。",
    "inputs": ["客户主营业务描述", "企业规模信息（员工数/年营收/注册资本至少一项）", "行业分类"],
    "outputs": ["场景判断结论（属于普惠/可能属于普惠/不属于普惠）", "适用客群分类", "政策依据层级", "产品候选方向", "边界提示"],
    "related_skills": [
      "skill.action.client-needs-diagnosis",
      "skill.action.product-matching-boundary",
      "skill.reference.problem-opportunity-framework",
      "skill.reference.corporate-client-coverage-lens"
    ],
    "related_knowledge": [
      "knowledge.banks.ceb.inclusive-finance.scenario-map",
      "knowledge.banks.ceb.inclusive-finance.scenario-map.modules.policy-background",
      "knowledge.banks.ceb.inclusive-finance.scenario-map.modules.scenario-overview",
      "knowledge.banks.ceb.inclusive-finance.scenario-map.modules.key-products"
    ],
    "related_prompts": []
  },
  {
    "id": "skill.reference.industry-analysis-basics",
    "type": "reference",
    "capability": "analyze",
    "title": "Industry Analysis Basics",
    "display_name_zh": "行业分析基础",
    "path": "skills/reference/industry-analysis-basics",
    "entry": "skills/reference/industry-analysis-basics/SKILL.md",
    "summary": "从银行对公业务视角，提供接触企业客户前或贷后管理中的行业分析判断框架，聚焦信用风险、周期位置和监管影响。",
    "audience": ["finance-learner", "bank-practitioner"],
    "task_patterns": ["行业分析", "行业判断", "行业风险", "行业周期", "生命周期判断", "波特五力", "行业结构", "竞争格局", "行业政策影响", "贷后行业跟踪", "首次接触看行业", "行业背景判断"],
    "when_to_use": "客户拜访前需要快速建立行业信用风险判断、贷后管理中需要判断行业周期变化对企业的影响、或撰写信审报告行业分析段落时。",
    "not_for": "需要具体行业深度知识（水泥、光伏等）、最新监管政策即时解读、或投资建议时。",
    "inputs": ["客户所处行业名称（精确到二级分类）", "客户主营业务描述", "近期公开行业政策或监管动态（可选）"],
    "outputs": ["行业生命周期位置", "波特五力风险权重", "监管敏感度评估", "周期位置判断", "信用风险评级（低/中/高）", "待验证事项"],
    "related_skills": [
      "skill.reference.enterprise-cash-flow-judgment",
      "skill.reference.financial-statement-reading-lens",
      "skill.action.client-needs-diagnosis",
      "skill.reference.corporate-client-coverage-lens",
      "skill.reference.problem-opportunity-framework",
      "skill.action.product-matching-boundary"
    ],
    "related_knowledge": [
      "knowledge.common.economics.business-basics",
      "knowledge.banks.ceb.corporate-settlement.basic-settlement"
    ],
    "related_prompts": []
  },
  {
    "id": "skill.reference.online-credit-solution-lens",
    "type": "reference",
    "capability": "analyze",
    "title": "Online Credit Solution Lens",
    "display_name_zh": "线上授信自动化审批方案视角",
    "path": "skills/reference/online-credit-solution-lens",
    "entry": "skills/reference/online-credit-solution-lens/SKILL.md",
    "summary": "为线上授信自动化审批业务方案提供判断框架，尤其聚焦“授信方案”章节与信息缺口识别。",
    "audience": ["bank-practitioner", "manager"],
    "task_patterns": [
      "线上授信方案怎么写",
      "自动化审批业务方案",
      "授信方案章节",
      "准入策略怎么想",
      "还缺什么资料",
      "场景金融方案草拟"
    ],
    "when_to_use": "起草或审阅线上授信自动化审批业务方案前，需要先判断场景、客群、授信方案主干和边界时。",
    "not_for": "直接给审批结论、内部制度口径、定价或时效承诺，或在没有基础事实时硬写完整方案。",
    "inputs": ["展业场景", "目标客群", "核心企业或平台情况", "已知风控和管理要求"],
    "outputs": ["判断框架", "信息缺口清单方向", "授信方案主干提醒", "人工确认边界"],
    "related_skills": [
      "skill.reference.online-credit-admission-strategy-patterns",
      "skill.action.online-credit-approval-solution-drafting",
      "skill.action.product-matching-boundary",
      "skill.action.client-needs-diagnosis"
    ],
    "related_knowledge": [],
    "related_prompts": [],
    "boundary": {
      "vs.online-credit-approval-solution-drafting": "判断框架 vs. 问答补数和章节草拟",
      "vs.online-credit-admission-strategy-patterns": "总框架 vs. 准入策略专项建议"
    }
  },
  {
    "id": "skill.action.online-credit-approval-solution-drafting",
    "type": "action",
    "capability": "execute",
    "title": "Online Credit Approval Solution Drafting",
    "display_name_zh": "线上授信自动化审批业务方案辅助撰写",
    "path": "skills/action/online-credit-approval-solution-drafting",
    "entry": "skills/action/online-credit-approval-solution-drafting/SKILL.md",
    "summary": "通过问答补数、识别缺口并草拟线上授信自动化审批业务方案，重点输出“授信方案”章节。",
    "audience": ["bank-practitioner", "manager"],
    "task_patterns": [
      "线上授信方案撰写",
      "自动化审批业务方案",
      "授信方案章节怎么写",
      "准入策略建议",
      "方案缺口清单",
      "分行方案草拟"
    ],
    "when_to_use": "需要通过问答方式收集信息并辅助起草线上授信自动化审批业务方案时。",
    "not_for": "直接代替内部审批、授信政策、定价或最终结论，或在没有任何基础事实时输出确定判断。",
    "inputs": ["展业场景", "目标客群", "核心企业或平台基本情况", "初步授信模式或还款来源"],
    "outputs": ["当前已掌握信息", "缺口清单", "需追问问题", "授信方案章节草稿", "准入策略建议草稿", "待人工确认项"],
    "related_skills": [
      "skill.reference.online-credit-solution-lens",
      "skill.reference.online-credit-admission-strategy-patterns",
      "skill.reference.executive-briefing-decision-support"
    ],
    "related_knowledge": [],
    "related_prompts": [
      "prompt.skill.action.online-credit-approval-solution-drafting"
    ]
  },
  {
    "id": "skill.reference.online-credit-admission-strategy-patterns",
    "type": "reference",
    "capability": "analyze",
    "title": "Online Credit Admission Strategy Patterns",
    "display_name_zh": "线上授信准入策略建议",
    "path": "skills/reference/online-credit-admission-strategy-patterns",
    "entry": "skills/reference/online-credit-admission-strategy-patterns/SKILL.md",
    "summary": "为线上授信自动化审批方案中的准入策略章节提供结构化建议框架，重点覆盖场景、主体、还款来源、数据、风险缓释和管理闭环。",
    "audience": ["bank-practitioner", "manager"],
    "task_patterns": [
      "准入策略怎么写",
      "线上授信准入",
      "自动化审批准入策略",
      "平台场景准入建议",
      "核心企业上下游准入建议",
      "授信方案准入章节"
    ],
    "when_to_use": "需要为线上授信自动化审批业务方案设计或审阅准入策略章节时。",
    "not_for": "直接输出内部准入阈值、评分规则、审批结论或定价期限口径。",
    "inputs": ["业务模式和场景", "核心企业或平台情况", "借款主体和还款来源", "数据与风控安排"],
    "outputs": ["准入策略建议维度", "场景观察重点", "待补资料提醒", "人工确认边界"],
    "related_skills": [
      "skill.reference.online-credit-solution-lens",
      "skill.action.online-credit-approval-solution-drafting",
      "skill.action.product-matching-boundary",
      "skill.reference.enterprise-cash-flow-judgment"
    ],
    "related_knowledge": [],
    "related_prompts": []
  },
  {
    "id": "skill.reference.branch-operating-diagnosis-lens",
    "type": "reference",
    "capability": "analyze",
    "title": "Branch Operating Diagnosis Lens",
    "display_name_zh": "经营分析视角",
    "path": "skills/reference/branch-operating-diagnosis-lens",
    "entry": "skills/reference/branch-operating-diagnosis-lens/SKILL.md",
    "summary": "为分支行、网点或团队经营分析提供判断框架，帮助区分结果问题、结构问题、原因层级和待补数项。",
    "audience": ["bank-practitioner", "manager"],
    "task_patterns": [
      "经营分析怎么看",
      "分行经营诊断",
      "网点经营分析",
      "结果和结构怎么区分",
      "经营短板怎么找",
      "先看哪些指标"
    ],
    "when_to_use": "拿到一组经营目标和关键经营数据后，需要先判断结果、结构、归因和待补数项时。",
    "not_for": "直接替代内部经营分析系统、正式考核结论或没有口径一致数据时硬下经营判断。",
    "inputs": ["经营目标", "关键经营数据", "同比/环比或上期对比", "自我评价或现场判断"],
    "outputs": ["结果判断", "结构判断", "初步归因", "待补数项", "边界提示"],
    "related_skills": [
      "skill.action.branch-operating-diagnosis",
      "skill.action.report-decision-brief",
      "skill.reference.executive-briefing-decision-support",
      "skill.action.interpret-financial-signal"
    ],
    "related_knowledge": [],
    "related_prompts": []
  },
  {
    "id": "skill.action.branch-operating-diagnosis",
    "type": "action",
    "capability": "analyze",
    "title": "Branch Operating Diagnosis",
    "display_name_zh": "经营分析",
    "path": "skills/action/branch-operating-diagnosis",
    "entry": "skills/action/branch-operating-diagnosis/SKILL.md",
    "summary": "通过对话收集经营目标、关键数据和自我评价，输出亮点、短板、初步归因和待补数项。",
    "audience": ["bank-practitioner", "manager"],
    "task_patterns": [
      "经营分析",
      "分行经营诊断",
      "网点经营分析",
      "经营亮点短板",
      "经营初判",
      "先看哪些数据"
    ],
    "when_to_use": "需要快速形成一版结构化经营分析初判时。",
    "not_for": "替代内部经营系统、正式考核结论，或在没有关键输入时强行输出完整经营判断。",
    "inputs": ["当前阶段目标", "关键经营数据", "至少一个对比维度", "自我评价或现场判断"],
    "outputs": ["当前初判", "亮点", "短板", "主要依据", "初步归因", "待补数项", "边界提示"],
    "related_skills": [
      "skill.reference.branch-operating-diagnosis-lens",
      "skill.action.operating-recommendation-brief",
      "skill.action.report-decision-brief",
      "skill.reference.executive-briefing-decision-support"
    ],
    "related_knowledge": [],
    "related_prompts": [
      "prompt.skill.action.branch-operating-diagnosis"
    ]
  },
  {
    "id": "skill.action.query-finhot",
    "type": "action",
    "capability": "retrieve",
    "title": "Query Finhot",
    "display_name_zh": "查询 Finhot 内容库",
    "path": "skills/action/query-finhot",
    "entry": "skills/action/query-finhot/SKILL.md",
    "summary": "从 Finhot 读取最新动态、产品、案例/模式、政策、观察和打法，并结合 Fincap skill 输出解读。",
    "audience": ["finance-learner", "bank-practitioner", "manager"],
    "task_patterns": [
      "最新动态",
      "Finhot 查询",
      "同业动作",
      "政策变化",
      "产品案例",
      "交易银行动态",
      "供应链金融动态",
      "产品能力地图",
      "客户经营线索"
    ],
    "when_to_use": "问题涉及最新公开信息、Finhot 已沉淀内容、或需要把 Fincap 判断框架与 Finhot 内容库联动时。",
    "not_for": "只需要稳定方法论、内部审批结论、或不能访问 Finhot API 时。",
    "inputs": ["关键词或问题", "期望分类（可选）", "使用场景"],
    "outputs": ["命中内容", "来源链接", "产品领域", "价值标签", "结构化解读", "落地建议", "待核验项"],
    "related_skills": [
      "skill.action.interpret-financial-signal",
      "skill.action.distill-and-curate",
      "skill.action.market-corporate-client",
      "skill.action.product-matching-boundary"
    ],
    "related_knowledge": [],
    "related_prompts": [
      "prompt.skill.action.query-finhot"
    ]
  }
]
